DO_analysis/DOC.py
DO_analysis/__init__.py
DO_analysis/diversity.py
DO_analysis-0.1.2.dist-info/LICENSE.txt
DO_analysis-0.1.2.dist-info/METADATA
DO_analysis-0.1.2.dist-info/WHEEL
DO_analysis-0.1.2.dist-info/top_level.txt
DO_analysis-0.1.2.dist-info/RECORD
