Metadata-Version: 2.1
Name: DO-analysis
Version: 0.1.2
Summary: A simple Python library for calculating Dissimilarity Overlap Curve and alpha/beta diversity
Download-URL: https://github.com/IvanovaVA/DOC_analysis/archive/refs/tags/0.1.0.tar.gz
Author: Valeriia Ivanova
License: MIT
License-File: LICENSE.txt
